{"assets/fonts/Montserrat-Bold.ttf":["assets/fonts/Montserrat-Bold.ttf"],"assets/fonts/Montserrat-Medium.ttf":["assets/fonts/Montserrat-Medium.ttf"],"assets/fonts/Montserrat-Regular.ttf":["assets/fonts/Montserrat-Regular.ttf"],"assets/images/ai_chat_bot.png":["assets/images/ai_chat_bot.png"],"assets/images/allpayment.png":["assets/images/allpayment.png"],"assets/images/cloud_connect.gif":["assets/images/cloud_connect.gif"],"assets/images/digitechbanner.png":["assets/images/digitechbanner.png"],"assets/images/dnb.png":["assets/images/dnb.png"],"assets/images/domain_available.png":["assets/images/domain_available.png"],"assets/images/dynadot.png":["assets/images/dynadot.png"],"assets/images/employee.jpg":["assets/images/employee.jpg"],"assets/images/final_join_us.png":["assets/images/final_join_us.png"],"assets/images/googleplay.png":["assets/images/googleplay.png"],"assets/images/icon.png":["assets/images/icon.png"],"assets/images/inventory.png":["assets/images/inventory.png"],"assets/images/logo.png":["assets/images/logo.png"],"assets/images/msme.png":["assets/images/msme.png"],"assets/images/no_internet.gif":["assets/images/no_internet.gif"],"assets/images/payment_qr.png":["assets/images/payment_qr.png"],"assets/images/risived.png":["assets/images/risived.png"],"assets/images/startup_india.png":["assets/images/startup_india.png"],"assets/images/step3.png":["assets/images/step3.png"],"assets/images/update_v.png":["assets/images/update_v.png"],"assets/translations/en-US.json":["assets/translations/en-US.json"],"assets/translations/hi-IN.json":["assets/translations/hi-IN.json"],"assets/translations/mr-IN.json":["assets/translations/mr-IN.json"],"packages/csc_picker/lib/assets/country.json":["packages/csc_picker/lib/assets/country.json"],"packages/cupertino_icons/assets/CupertinoIcons.ttf":["packages/cupertino_icons/assets/CupertinoIcons.ttf"],"packages/flutter_map/lib/assets/flutter_map_logo.png":["packages/flutter_map/lib/assets/flutter_map_logo.png"],"packages/fluttertoast/assets/toastify.css":["packages/fluttertoast/assets/toastify.css"],"packages/fluttertoast/assets/toastify.js":["packages/fluttertoast/assets/toastify.js"],"packages/wakelock_plus/assets/no_sleep.js":["packages/wakelock_plus/assets/no_sleep.js"]}